sphinxcontrib_gitloginfo-1.1.0-py3.8-nspkg.pth
sphinxcontrib/__pycache__/__init__.cpython-37.pyc
sphinxcontrib/gitloginfo/__init__.py
sphinxcontrib/gitloginfo/__init__.pyc
sphinxcontrib/gitloginfo/version.py
sphinxcontrib/gitloginfo/version.pyc
sphinxcontrib/gitloginfo/__pycache__/__init__.cpython-38.pyc
sphinxcontrib_gitloginfo-1.1.0.dist-info/AUTHORS.rst
sphinxcontrib_gitloginfo-1.1.0.dist-info/LICENSE
sphinxcontrib_gitloginfo-1.1.0.dist-info/METADATA
sphinxcontrib_gitloginfo-1.1.0.dist-info/WHEEL
sphinxcontrib_gitloginfo-1.1.0.dist-info/namespace_packages.txt
sphinxcontrib_gitloginfo-1.1.0.dist-info/pbr.json
sphinxcontrib_gitloginfo-1.1.0.dist-info/top_level.txt
sphinxcontrib_gitloginfo-1.1.0.dist-info/RECORD
