Metadata-Version: 2.1
Name: sphinxcontrib-gitloginfo
Version: 1.1.0
Summary: Sphinx extension to provide data obtained from "git log" in the Sphinx page rendering context.
Home-page: https://github.com/TYPO3-Documentation/sphinxcontrib-gitloginfo
Author: Martin Bless
Author-email: martin.bless@mbless.de
License: MIT license
Download-URL: https://pypi.org/project/sphinxcontrib-gitloginfo/
Platform: any
Classifier: Development Status :: 5 - Production/Stable
Classifier: Framework :: Sphinx :: Extension
Classifier: Framework :: Sphinx
Classifier: Intended Audience :: Developers
Classifier: License :: OSI Approved :: MIT License
Classifier: Operating System :: OS Independent
Classifier: Programming Language :: Python :: 2
Classifier: Programming Language :: Python :: 2.7
Classifier: Programming Language :: Python :: 3
Classifier: Programming Language :: Python :: 3.5
Classifier: Programming Language :: Python :: 3.6
Classifier: Programming Language :: Python :: 3.7
Classifier: Programming Language :: Python :: 3.8
Classifier: Programming Language :: Python
Classifier: Topic :: Documentation :: Sphinx
Classifier: Topic :: Documentation
Requires-Python: >=2.7, !=3.0.*, !=3.1.*, !=3.2.*, !=3.3.*, !=3.4.*
Provides-Extra: test
Requires-Dist: pytest ; extra == 'test'
Requires-Dist: flake8 ; extra == 'test'
Requires-Dist: mypy ; extra == 'test'
